CHANGELOG.md
MANIFEST.in
README.md
setup.py
stdeb.cfg
vcs_extras/__init__.py
vcs_extras/console.py
vcs_extras.egg-info/PKG-INFO
vcs_extras.egg-info/SOURCES.txt
vcs_extras.egg-info/dependency_links.txt
vcs_extras.egg-info/entry_points.txt
vcs_extras.egg-info/requires.txt
vcs_extras.egg-info/top_level.txt
vcs_extras/vci/__init__.py
vcs_extras/vci/argument_parsing.py
vcs_extras/vci/common.py
vcs_extras/vci/config.py
vcs_extras/vci/find.py
vcs_extras/vci/index_contents.py