Metadata-Version: 1.1
Name: vcs-extras
Version: 0.1.2
Summary: extra commands for working with vcstool
Home-page: http://github.com/stonier/vcs_extras
Author: Daniel Stonier
Author-email: d.stonier@gmail.com
License: BSD
Keywords: catkin
Platform: UNKNOWN
Classifier: Environment :: Console
Classifier: Intended Audience :: Developers
Classifier: License :: OSI Approved :: BSD License
Classifier: Programming Language :: Python
Classifier: Topic :: Software Development :: Version Control
Classifier: Topic :: Utilities
